levis_pdfparse-0.1.0.data/scripts/serve_grobid.sh
scipdf/__init__.py
scipdf/features/__init__.py
scipdf/features/text_utils.py
scipdf/pdf/__init__.py
scipdf/pdf/parse_pdf.py
scipdf/pdf/pdffigures2/pdffigures2-assembly-0.0.12-SNAPSHOT.jar
levis_pdfparse-0.1.0.dist-info/LICENSE.txt
levis_pdfparse-0.1.0.dist-info/METADATA
levis_pdfparse-0.1.0.dist-info/WHEEL
levis_pdfparse-0.1.0.dist-info/top_level.txt
levis_pdfparse-0.1.0.dist-info/RECORD
