Metadata-Version: 2.1
Name: levis-pdfparse
Version: 0.1.0
Summary: Python parser for scientific PDF based on GROBID.
Home-page: https://github.com/lynner-haode/pdf_parser
Author: Levis
Author-email: lynner.haode@gmail.com
License: (c) MIT License 2023 Levis
Keywords: SCI,PDF parser,GROBID,Python PDF parser
Classifier: Programming Language :: Python :: 3
Classifier: License :: OSI Approved :: MIT License
Classifier: Operating System :: OS Independent
License-File: LICENSE.txt
Requires-Dist: lxml
Requires-Dist: requests
Requires-Dist: spacy
Requires-Dist: pandas
Requires-Dist: textstat
